{"version":1,"resource":"file:///Users/ivantelizhenko/Desktop/vscode/redux%2Bts/src/components/CartItems.tsx","entries":[{"id":"CZxU.tsx","timestamp":1738662271271},{"id":"rl31.tsx","timestamp":1738662285183},{"id":"ieYF.tsx","timestamp":1738662305354},{"id":"mcsx.tsx","timestamp":1738662323939},{"id":"dElO.tsx","timestamp":1738662335959},{"id":"6l9C.tsx","timestamp":1738662365962},{"id":"J5jl.tsx","timestamp":1738662380869},{"id":"nb5k.tsx","timestamp":1738662423390},{"id":"pB4V.tsx","timestamp":1738662440452},{"id":"2pwo.tsx","timestamp":1738662512802},{"id":"uyWY.tsx","timestamp":1738662543469},{"id":"1Z6T.tsx","timestamp":1738662566274},{"id":"6MAZ.tsx","timestamp":1738662609082},{"id":"SH5x.tsx","timestamp":1738662691149}]}