{"version":1,"resource":"file:///Users/ivantelizhenko/Desktop/vscode/quest-app/app/components/AddNewQuest/Box.tsx","entries":[{"id":"h1a7.tsx","timestamp":1739097744186},{"id":"SamA.tsx","timestamp":1739097777115},{"id":"JWgT.tsx","timestamp":1739098014421},{"id":"Zxq1.tsx","timestamp":1739098024831},{"id":"gktk.tsx","timestamp":1739098039892},{"id":"ghpc.tsx","timestamp":1739098052549},{"id":"01qt.tsx","timestamp":1739098084706},{"id":"iTzV.tsx","timestamp":1739098945583},{"id":"sate.tsx","timestamp":1739098961406},{"id":"wm6v.tsx","timestamp":1739098991169},{"id":"Xzu3.tsx","timestamp":1739099625982},{"id":"AwNI.tsx","timestamp":1739099636106},{"id":"Yhaf.tsx","timestamp":1739108284658},{"id":"ohk0.tsx","timestamp":1739108302311},{"id":"ZfwW.tsx","timestamp":1739108316604},{"id":"ZveL.tsx","timestamp":1739108435547},{"id":"qC9S.tsx","timestamp":1739108453921},{"id":"8zqP.tsx","timestamp":1739109183732},{"id":"xSi8.tsx","timestamp":1739191268505},{"id":"kZ86.tsx","timestamp":1739191361664},{"id":"i3o2.tsx","timestamp":1739191373436},{"id":"oxwG.tsx","timestamp":1739192099481},{"id":"kUFN.tsx","timestamp":1739192123767},{"id":"RMPD.tsx","timestamp":1739192413559},{"id":"7QpD.tsx","timestamp":1739203326293},{"id":"OjDP.tsx","timestamp":1739203336947},{"id":"0shu.tsx","timestamp":1739355983434}]}