{"version":1,"resource":"file:///Users/ivantelizhenko/Desktop/vscode/work%20with%20components/03-table.html","entries":[{"id":"DMAc.html","source":"Paste component copy.html","timestamp":1695674560201},{"id":"yNWC.html","source":"renamed.source","timestamp":1695674560622},{"id":"lJck.html","timestamp":1695674580750},{"id":"AiuP.html","timestamp":1695674632182},{"id":"cXIs.html","timestamp":1695675295693},{"id":"GVch.html","timestamp":1695675566642},{"id":"OaVF.html","timestamp":1695675592253},{"id":"rDjT.html","timestamp":1695675686482},{"id":"JJ4I.html","timestamp":1695675770177},{"id":"s7CF.html","timestamp":1695675978235},{"id":"HXUh.html","timestamp":1695676551797},{"id":"DWqq.html","timestamp":1695676586340},{"id":"0NBj.html","timestamp":1695676605806},{"id":"3QH3.html","timestamp":1695676629336},{"id":"eaZK.html","timestamp":1695676652631},{"id":"7gG0.html","timestamp":1695676668924},{"id":"Z6M4.html","timestamp":1695676737003},{"id":"5lEF.html","timestamp":1695676798202},{"id":"mA8C.html","timestamp":1695676840828},{"id":"efl2.html","timestamp":1695676874020},{"id":"Xq1m.html","timestamp":1695676899142},{"id":"aFBY.html","timestamp":1695676928567},{"id":"WAPE.html","timestamp":1695676961271},{"id":"YBJ1.html","timestamp":1695677045553},{"id":"Q8Eq.html","timestamp":1695677056713},{"id":"88KL.html","timestamp":1695677068041},{"id":"mLJR.html","timestamp":1695677094818},{"id":"rOO0.html","timestamp":1695677153816},{"id":"wZVc.html","timestamp":1695677184232},{"id":"EaxC.html","timestamp":1695677212310},{"id":"3Keg.html","timestamp":1695677266295},{"id":"qQsh.html","timestamp":1695677310620},{"id":"gFTl.html","timestamp":1695677344973},{"id":"bzGd.html","timestamp":1695677382514},{"id":"GPBe.html","timestamp":1695677394553},{"id":"HaNF.html","timestamp":1695677419856},{"id":"9GC7.html","timestamp":1695677433853},{"id":"Up85.html","timestamp":1695677529297},{"id":"9KFe.html","timestamp":1695677625891},{"id":"LjgD.html","timestamp":1695677664501},{"id":"UP8y.html","timestamp":1695677699023},{"id":"wlo9.html","timestamp":1695677719495},{"id":"76f3.html","timestamp":1695677732727},{"id":"SEtW.html","timestamp":1695677750559}]}