{"version":1,"resource":"file:///Users/ivantelizhenko/Desktop/vscode/unsprinkle-v2/src/components/App/App.jsx","entries":[{"id":"eqav.jsx","timestamp":1743849096583},{"id":"vcOo.jsx","timestamp":1743849235559},{"id":"2nek.jsx","timestamp":1743850616489},{"id":"awji.jsx","timestamp":1743850631722},{"id":"wYuk.jsx","timestamp":1743850644589},{"id":"ebGk.jsx","timestamp":1743850761999},{"id":"7Zmv.jsx","source":"Workspace Edit","timestamp":1743850805062},{"id":"Ho7K.jsx","timestamp":1743850831434},{"id":"6sGE.jsx","timestamp":1743850868462},{"id":"yIfB.jsx","timestamp":1743850899932},{"id":"WpRx.jsx","timestamp":1743850929949},{"id":"LBfe.jsx","timestamp":1743850942597},{"id":"RGiY.jsx","timestamp":1743850976732},{"id":"Yw4e.jsx","timestamp":1743851026720},{"id":"ipar.jsx","timestamp":1743851092290},{"id":"6gKQ.jsx","source":"Workspace Edit","timestamp":1743851101566},{"id":"fpFI.jsx","timestamp":1743851106113}]}