{"version":1,"resource":"file:///Users/ivantelizhenko/Desktop/vscode/Bits%20Orchestra%20Test%20Task/src/components/Footer.tsx","entries":[{"id":"rLyJ.tsx","timestamp":1741592932839},{"id":"J8eB.tsx","timestamp":1741592959881},{"id":"FgBR.tsx","timestamp":1741593009903},{"id":"ibj3.tsx","timestamp":1741593668210},{"id":"dhLC.tsx","timestamp":1741593694388},{"id":"YmrM.tsx","timestamp":1741594000532},{"id":"CmuH.tsx","timestamp":1741623958012},{"id":"149c.tsx","timestamp":1741623979948},{"id":"0pyF.tsx","timestamp":1741623996766},{"id":"BZBC.tsx","timestamp":1741624008525},{"id":"JJOd.tsx","timestamp":1741624026139},{"id":"5gJa.tsx","timestamp":1741624050630},{"id":"FEF1.tsx","timestamp":1741624076663},{"id":"P8IL.tsx","timestamp":1741624090350},{"id":"zrfA.tsx","timestamp":1741624105538},{"id":"HUHL.tsx","timestamp":1741624186016},{"id":"f1A9.tsx","timestamp":1741624199426},{"id":"dHdt.tsx","timestamp":1741624224521},{"id":"uSdX.tsx","timestamp":1741624246539},{"id":"CbXl.tsx","timestamp":1741624301268},{"id":"AIY7.tsx","timestamp":1741624362293}]}