{"version":1,"resource":"file:///Users/ivantelizhenko/Desktop/practice%201/menu/menu-index.html","entries":[{"id":"ITaG.html","timestamp":1698783335390},{"id":"2lR1.html","timestamp":1698783400080},{"id":"Rr09.html","timestamp":1698783475076},{"id":"IvXu.html","timestamp":1698783566286},{"id":"F2gG.html","source":"undoRedo.source","timestamp":1698783585146},{"id":"95Yj.html","timestamp":1698783599969},{"id":"m0qe.html","timestamp":1698783629316},{"id":"IGSn.html","timestamp":1698783649416},{"id":"TXc7.html","timestamp":1698783680253},{"id":"tR5k.html","timestamp":1698783712858},{"id":"iwNC.html","timestamp":1698783726685},{"id":"4jTb.html","timestamp":1698783750976},{"id":"Jpay.html","timestamp":1698783966316},{"id":"doC6.html","timestamp":1698784024477},{"id":"jTd4.html","timestamp":1698784158415},{"id":"2LCs.html","timestamp":1698784912536},{"id":"ZyON.html","timestamp":1698840124763},{"id":"iDX0.html","timestamp":1698840276548},{"id":"rXZV.html","timestamp":1698840293773},{"id":"9KN6.html","timestamp":1698840356356},{"id":"d5AC.html","timestamp":1698840422933},{"id":"9X0H.html","timestamp":1698841270362},{"id":"8E66.html","timestamp":1698841295016},{"id":"ESAG.html","timestamp":1698841624913},{"id":"EhjV.html","timestamp":1698841715233},{"id":"5CBT.html","timestamp":1698841771734},{"id":"kyQT.html","timestamp":1698841783918},{"id":"aNPn.html","timestamp":1698841805019},{"id":"FqrF.html","timestamp":1698841820167},{"id":"FTjY.html","timestamp":1698841837845},{"id":"ld06.html","timestamp":1698841891042},{"id":"fnB7.html","timestamp":1698841906643},{"id":"YM4e.html","timestamp":1698841952919},{"id":"cBKM.html","timestamp":1698841986174},{"id":"CxlZ.html","timestamp":1698842297188},{"id":"FKM9.html","source":"undoRedo.source","timestamp":1698844461161},{"id":"ufbb.html","timestamp":1698844467919},{"id":"ncZD.html","timestamp":1698844511158},{"id":"MHE7.html","timestamp":1698844545224},{"id":"5Rpv.html","timestamp":1698845054586},{"id":"ooqo.html","timestamp":1698846080671},{"id":"rdMJ.html","timestamp":1698846100830},{"id":"xqHy.html","timestamp":1698846768715},{"id":"h8Fv.html","timestamp":1698846834229},{"id":"aEGp.html","timestamp":1698846996118},{"id":"TWVR.html","source":"moved.source","timestamp":1698847454345},{"id":"97Ob.html","source":"moved.source","timestamp":1698847457271},{"id":"AYgq.html","timestamp":1698847507655},{"id":"wwdU.html","timestamp":1698847777157},{"id":"T3rE.html","timestamp":1698862678424}]}