{"version":1,"resource":"file:///Users/ivantelizhenko/Desktop/vscode/character-creator-v2/src/components/CharacterEditor/CharacterEditor.module.css","entries":[{"id":"5PrJ.css","timestamp":1741194349074},{"id":"Z70k.css","timestamp":1741194406040},{"id":"ukUr.css","timestamp":1741194418979},{"id":"0uBC.css","timestamp":1741194462565},{"id":"Ahsy.css","timestamp":1741194497845},{"id":"ddM6.css","timestamp":1741194508059},{"id":"vDxB.css","timestamp":1741194522281},{"id":"Qa8t.css","timestamp":1741194542899},{"id":"ZhK5.css","timestamp":1741194598069},{"id":"2w6t.css","timestamp":1741194623048},{"id":"Iazz.css","timestamp":1741194646225},{"id":"96jA.css","timestamp":1741194678366},{"id":"tg8P.css","timestamp":1741194689671},{"id":"WZGU.css","timestamp":1741194718100},{"id":"kLWl.css","source":"undoRedo.source","timestamp":1741194720666},{"id":"m4iX.css","timestamp":1741194732191},{"id":"eIck.css","source":"undoRedo.source","timestamp":1741194735017},{"id":"Bmfb.css","timestamp":1741194741480},{"id":"w4K2.css","source":"undoRedo.source","timestamp":1741194744044},{"id":"pSsQ.css","timestamp":1741194748462},{"id":"vnK2.css","timestamp":1741194781457},{"id":"rPf5.css","timestamp":1741194794646},{"id":"AmD9.css","timestamp":1741194839733},{"id":"HlAr.css","timestamp":1741194885981},{"id":"97Fn.css","timestamp":1741194905194},{"id":"Dae1.css","timestamp":1741194935548},{"id":"ATWM.css","timestamp":1741194947274},{"id":"uOK6.css","timestamp":1741194991845},{"id":"sT2d.css","timestamp":1741195003678},{"id":"pmZK.css","timestamp":1741195023797},{"id":"lxjE.css","timestamp":1741195116968},{"id":"6MRn.css","timestamp":1741195185539},{"id":"fEoI.css","timestamp":1741195214424},{"id":"PgKH.css","timestamp":1741195248998},{"id":"eQ5i.css","timestamp":1741195261848},{"id":"KZt0.css","timestamp":1741195292169},{"id":"F53e.css","timestamp":1741195318013},{"id":"51Zw.css","timestamp":1741195330367},{"id":"uV7x.css","timestamp":1741195357395},{"id":"JIYh.css","timestamp":1741195368752},{"id":"BhvL.css","timestamp":1741195420938},{"id":"bkJu.css","timestamp":1741195443094},{"id":"hIG2.css","timestamp":1741195466585},{"id":"OYj4.css","timestamp":1741195485738},{"id":"EoiD.css","timestamp":1741195497612},{"id":"6sN8.css","timestamp":1741195593958},{"id":"jP5c.css","timestamp":1741195636237},{"id":"UCAW.css","timestamp":1741195667964},{"id":"JG2Q.css","timestamp":1741195690054},{"id":"osqw.css","timestamp":1741195764250}]}