{"version":1,"resource":"file:///Users/ivantelizhenko/Desktop/vscode/COURSES/React/17-the-wild-oasis/src/ui/Heading.jsx","entries":[{"id":"txAu.jsx","timestamp":1721744621600},{"id":"PPpq.jsx","source":"undoRedo.source","timestamp":1721744634791},{"id":"JIh5.jsx","timestamp":1721744640149},{"id":"aKML.jsx","source":"renamed.source","timestamp":1721744642589},{"id":"r1od.jsx","timestamp":1721744654563},{"id":"UNRU.jsx","timestamp":1721744665050},{"id":"MhMU.jsx","timestamp":1721744715527},{"id":"tLhu.jsx","timestamp":1721744817848},{"id":"XAwS.jsx","timestamp":1721744828818},{"id":"DWkU.jsx","timestamp":1721744844871},{"id":"IdVz.jsx","timestamp":1721745488647},{"id":"bz7W.jsx","timestamp":1721745571013},{"id":"N9bB.jsx","timestamp":1721745670616},{"id":"cYht.jsx","timestamp":1721745711472},{"id":"NlBP.jsx","timestamp":1721745737674},{"id":"J9dJ.jsx","timestamp":1721746092953},{"id":"piXN.jsx","timestamp":1721746123382},{"id":"Rmsw.jsx","timestamp":1721746144627},{"id":"pPxP.jsx","timestamp":1721746194958},{"id":"K8Y6.jsx","timestamp":1721746273519},{"id":"uQVh.jsx","timestamp":1721746363020},{"id":"MmTp.jsx","timestamp":1721746460832},{"id":"zubt.jsx","timestamp":1721748559427},{"id":"22fK.jsx","timestamp":1724508656846},{"id":"U3A5.jsx","timestamp":1724508761900}]}