{"version":1,"resource":"file:///Users/ivantelizhenko/Desktop/vscode/login%20page/queries.css","entries":[{"id":"vzmR.css","timestamp":1709496065278},{"id":"nvpZ.css","timestamp":1709496152185},{"id":"vmG8.css","timestamp":1709496170560},{"id":"UdeB.css","timestamp":1709496191878},{"id":"Tpiy.css","timestamp":1709496208530},{"id":"s5qe.css","timestamp":1709496239282},{"id":"i0uA.css","timestamp":1709496251073},{"id":"v2nA.css","timestamp":1709496264996},{"id":"LHQz.css","timestamp":1709496306886},{"id":"zjte.css","timestamp":1709496333336},{"id":"cN3O.css","source":"undoRedo.source","timestamp":1709496337879},{"id":"Kl7i.css","timestamp":1709496388526},{"id":"C0xP.css","timestamp":1709496405542},{"id":"hXzB.css","timestamp":1709496451276},{"id":"nwdi.css","timestamp":1709496481070},{"id":"ztq1.css","timestamp":1709496507563},{"id":"MDKF.css","timestamp":1709496519809},{"id":"MptD.css","timestamp":1709496552625},{"id":"IE0S.css","timestamp":1709496622683},{"id":"y7E7.css","timestamp":1709496632866},{"id":"FLkr.css","timestamp":1709496653942},{"id":"HFhF.css","timestamp":1709496675915},{"id":"NfZZ.css","timestamp":1709496714594},{"id":"PJP1.css","timestamp":1709496737064},{"id":"NKpk.css","timestamp":1709496756785},{"id":"EO5q.css","timestamp":1709496777484},{"id":"3sKn.css","timestamp":1709496802608},{"id":"5dzb.css","timestamp":1709496948512},{"id":"eiVM.css","timestamp":1709496958878},{"id":"l76s.css","timestamp":1709496971367},{"id":"SFJX.css","timestamp":1709496998111},{"id":"X89l.css","timestamp":1709497012383},{"id":"I2G7.css","timestamp":1709497030857},{"id":"tnEU.css","source":"undoRedo.source","timestamp":1709497033856}]}