{"version":1,"resource":"file:///Users/ivantelizhenko/Desktop/vscode/COURSES/Course%20Sass/Nexter/sass/_realtors.scss","entries":[{"id":"9M8j.scss","timestamp":1711829438540},{"id":"8bwX.scss","timestamp":1711829457618},{"id":"of8v.scss","timestamp":1711884961843},{"id":"VKUB.scss","timestamp":1712426076271},{"id":"1zxU.scss","timestamp":1712426088916},{"id":"vKDL.scss","timestamp":1712426104555},{"id":"q5ma.scss","timestamp":1712426114841},{"id":"0tGT.scss","timestamp":1712426127230},{"id":"U2CZ.scss","timestamp":1712426150550},{"id":"I1gP.scss","timestamp":1712426173744},{"id":"Qddq.scss","timestamp":1712426190231},{"id":"n2Ja.scss","timestamp":1712426247557},{"id":"z1ss.scss","timestamp":1712426260853},{"id":"Rfux.scss","timestamp":1712426302476},{"id":"4Adh.scss","timestamp":1712426320510},{"id":"JJ9z.scss","timestamp":1712426377288},{"id":"2OQg.scss","timestamp":1712426404084},{"id":"bOX0.scss","timestamp":1712426420152},{"id":"A3Gw.scss","timestamp":1712426443813},{"id":"41t9.scss","timestamp":1712426479604},{"id":"tPg6.scss","timestamp":1712431803667},{"id":"Rvs6.scss","timestamp":1712431839126},{"id":"YxAE.scss","timestamp":1712431862779},{"id":"Zy4U.scss","timestamp":1712432612724}]}