{"version":1,"resource":"file:///Users/ivantelizhenko/Desktop/vscode/test/insiders-test/src/services/AJAX.ts","entries":[{"id":"WnsA.ts","timestamp":1736785605955},{"id":"vmdC.ts","timestamp":1736785628621},{"id":"m8CJ.ts","timestamp":1736785639666},{"id":"wTE3.ts","timestamp":1736785944802},{"id":"6XuQ.ts","timestamp":1736785958148},{"id":"2n6J.ts","timestamp":1736786051102},{"id":"vVYf.ts","timestamp":1736786074025},{"id":"mgh3.ts","timestamp":1736786085297},{"id":"LaZ4.ts","timestamp":1736786103450},{"id":"wKHm.ts","timestamp":1736786161815},{"id":"Rf5u.ts","timestamp":1736786227995},{"id":"xQA4.ts","timestamp":1736786251246},{"id":"0ADP.ts","timestamp":1736786280590},{"id":"nPyY.ts","source":"renamed.source","sourceDescription":"~/Desktop/vscode/test/insiders-test/src/services/apiCountries.ts","timestamp":1736786291177},{"id":"g4m7.ts","timestamp":1736786299322},{"id":"K12f.ts","timestamp":1736786340989},{"id":"hbMb.ts","timestamp":1736786365473},{"id":"RyXE.ts","timestamp":1736786377793},{"id":"Bqe3.ts","source":"undoRedo.source","timestamp":1736786379971},{"id":"mr6w.ts","timestamp":1736786381750},{"id":"8cDh.ts","timestamp":1736786429311},{"id":"aY5X.ts","timestamp":1736786879305},{"id":"yso5.ts","timestamp":1736786894872},{"id":"pB4f.ts","timestamp":1736786917002},{"id":"1V1w.ts","timestamp":1736787031805},{"id":"knE2.ts","timestamp":1736787067732},{"id":"ovXe.ts","timestamp":1736787115332},{"id":"DsWY.ts","timestamp":1736787135490},{"id":"MS6t.ts","timestamp":1736787198842},{"id":"YjdC.ts","timestamp":1736787276850},{"id":"tXjp.ts","timestamp":1736787401107},{"id":"Iezd.ts","timestamp":1736792641587},{"id":"B7xb.ts","timestamp":1737231438994},{"id":"TItA.ts","timestamp":1737231673816},{"id":"cnXs.ts","timestamp":1737231752078},{"id":"Rinw.ts","timestamp":1737231785744},{"id":"lbyl.ts","timestamp":1737231816268},{"id":"zGkN.ts","timestamp":1737231827317},{"id":"vcS4.ts","timestamp":1737231839732},{"id":"MQzi.ts","timestamp":1737231880632},{"id":"DBpg.ts","timestamp":1737231900258},{"id":"3NWe.ts","timestamp":1737232232424},{"id":"bJdq.ts","timestamp":1737377377216},{"id":"JLLn.ts","timestamp":1737377418262},{"id":"uyF9.ts","timestamp":1737377446804},{"id":"bVUB.ts","timestamp":1737477176532},{"id":"EAcY.ts","timestamp":1737477197256},{"id":"s2dp.ts","timestamp":1737477224007},{"id":"NEzW.ts","timestamp":1737477238266},{"id":"23ij.ts","source":"Workspace Edit","timestamp":1737574231411}]}