{"version":1,"resource":"file:///Users/ivantelizhenko/Desktop/vscode/COURSES/React/17-the-wild-oasis/src/hooks/useOutsideClick.js","entries":[{"id":"A5HB.js","timestamp":1722797257704},{"id":"sPbm.js","source":"Workspace Edit","timestamp":1722797259610},{"id":"p32M.js","timestamp":1722797271167},{"id":"zeBq.js","timestamp":1722797293229},{"id":"7BPZ.js","timestamp":1722797425956},{"id":"FWca.js","timestamp":1722797459765},{"id":"iQ8n.js","timestamp":1722797480943},{"id":"UBIw.js","timestamp":1722797541833},{"id":"jpGq.js","timestamp":1722797559918},{"id":"CSqI.js","timestamp":1722797576369},{"id":"k1LD.js","timestamp":1722797591084},{"id":"O2mS.js","source":"moved.source","timestamp":1722797684323},{"id":"sCvq.js","source":"renamed.source","timestamp":1722797731639},{"id":"SA7p.js","timestamp":1722797734236},{"id":"1gta.js","timestamp":1722797773315},{"id":"pKXI.js","timestamp":1722797805484},{"id":"Qqx8.js","timestamp":1722797844763},{"id":"31ln.js","timestamp":1722850696523}]}