{"version":1,"resource":"file:///Users/ivantelizhenko/Desktop/vscode/insiders__test--2/src/Components/Form/Input.tsx","entries":[{"id":"KBAU.tsx","timestamp":1742287072414},{"id":"M1AS.tsx","timestamp":1742287100580},{"id":"eMTO.tsx","timestamp":1742287129828},{"id":"uJDK.tsx","timestamp":1742287155831},{"id":"TrvY.tsx","timestamp":1742287185669},{"id":"KLKj.tsx","timestamp":1742287202680},{"id":"M75L.tsx","timestamp":1742287248716},{"id":"5dul.tsx","timestamp":1742287260200},{"id":"fzFI.tsx","timestamp":1742287278302},{"id":"820I.tsx","timestamp":1742287504437},{"id":"IXrT.tsx","timestamp":1742287522629},{"id":"17M9.tsx","timestamp":1742289977646},{"id":"HNsr.tsx","timestamp":1742291584874},{"id":"WlEk.tsx","timestamp":1742291610879},{"id":"tBj1.tsx","timestamp":1742291631704},{"id":"ZOqD.tsx","timestamp":1742291656839}]}